postgres_product/__init__.py
postgres_product/aggregates.py
postgres_product/migrations/0001_product_aggregate.py
postgres_product/migrations/__init__.py
django_postgres_product-1.0.2.dist-info/LICENSE
django_postgres_product-1.0.2.dist-info/METADATA
django_postgres_product-1.0.2.dist-info/WHEEL
django_postgres_product-1.0.2.dist-info/top_level.txt
django_postgres_product-1.0.2.dist-info/RECORD
